<?xml version="1.0" encoding="UTF-8"?>
<GenRun Id="impl_1" LaunchPart="xc7a35tcpg236-1" LaunchTime="1575842651">
  <File Type="WBT-USG" Name="usage_statistics_webtalk.html"/>
  <File Type="BG-DRC" Name="metronome.drc"/>
  <File Type="BG-BGN" Name="metronome.bgn"/>
  <File Type="BITSTR-SYSDEF" Name="metronome.sysdef"/>
  <File Type="BITSTR-LTX" Name="debug_nets.ltx"/>
  <File Type="BITSTR-LTX" Name="metronome.ltx"/>
  <File Type="BITSTR-MMI" Name="metronome.mmi"/>
  <File Type="BITSTR-BMM" Name="metronome_bd.bmm"/>
  <File Type="BITSTR-NKY" Name="metronome.nky"/>
  <File Type="BITSTR-RBT" Name="metronome.rbt"/>
  <File Type="BITSTR-MSK" Name="metronome.msk"/>
  <File Type="BG-BIN" Name="metronome.bin"/>
  <File Type="BG-BIT" Name="metronome.bit"/>
  <File Type="POSTROUTE-PHYSOPT-BUS-SKEW-RPX" Name="metronome_bus_skew_postroute_physopted.rpx"/>
  <File Type="POSTROUTE-PHYSOPT-BUS-SKEW-PB" Name="metronome_bus_skew_postroute_physopted.pb"/>
  <File Type="POSTROUTE-PHYSOPT-BUS-SKEW" Name="metronome_bus_skew_postroute_physopted.rpt"/>
  <File Type="RDI-RDI" Name="metronome.vdi"/>
  <File Type="POSTROUTE-PHYSOPT-TIMING-RPX" Name="metronome_timing_summary_postroute_physopted.rpx"/>
  <File Type="POSTROUTE-PHYSOPT-TIMING-PB" Name="metronome_timing_summary_postroute_physopted.pb"/>
  <File Type="POSTROUTE-PHYSOPT-TIMING" Name="metronome_timing_summary_postroute_physopted.rpt"/>
  <File Type="POSTROUTE-PHYSOPT-BLACKBOX-DCP" Name="metronome_postroute_physopt_bb.dcp"/>
  <File Type="POSTROUTE-PHYSOPT-DCP" Name="metronome_postroute_physopt.dcp"/>
  <File Type="ROUTE-BUS-SKEW" Name="metronome_bus_skew_routed.rpt"/>
  <File Type="ROUTE-CLK" Name="metronome_clock_utilization_routed.rpt"/>
  <File Type="ROUTE-SIMILARITY" Name="metronome_incremental_reuse_routed.rpt"/>
  <File Type="ROUTE-TIMING-RPX" Name="metronome_timing_summary_routed.rpx"/>
  <File Type="ROUTE-TIMING-PB" Name="metronome_timing_summary_routed.pb"/>
  <File Type="ROUTE-TIMINGSUMMARY" Name="metronome_timing_summary_routed.rpt"/>
  <File Type="ROUTE-STATUS-PB" Name="metronome_route_status.pb"/>
  <File Type="ROUTE-STATUS" Name="metronome_route_status.rpt"/>
  <File Type="ROUTE-PWR-RPX" Name="metronome_power_routed.rpx"/>
  <File Type="ROUTE-PWR-SUM" Name="metronome_power_summary_routed.pb"/>
  <File Type="ROUTE-PWR" Name="metronome_power_routed.rpt"/>
  <File Type="ROUTE-METHODOLOGY-DRC-PB" Name="metronome_methodology_drc_routed.pb"/>
  <File Type="ROUTE-METHODOLOGY-DRC-RPX" Name="metronome_methodology_drc_routed.rpx"/>
  <File Type="ROUTE-METHODOLOGY-DRC" Name="metronome_methodology_drc_routed.rpt"/>
  <File Type="ROUTE-DRC-RPX" Name="metronome_drc_routed.rpx"/>
  <File Type="ROUTE-DRC-PB" Name="metronome_drc_routed.pb"/>
  <File Type="ROUTE-DRC" Name="metronome_drc_routed.rpt"/>
  <File Type="ROUTE-BLACKBOX-DCP" Name="metronome_routed_bb.dcp"/>
  <File Type="ROUTE-DCP" Name="metronome_routed.dcp"/>
  <File Type="ROUTE-ERROR-DCP" Name="metronome_routed_error.dcp"/>
  <File Type="PHYSOPT-TIMING" Name="metronome_timing_summary_physopted.rpt"/>
  <File Type="PHYSOPT-DRC" Name="metronome_drc_physopted.rpt"/>
  <File Type="PHYSOPT-DCP" Name="metronome_physopt.dcp"/>
  <File Type="POSTPLACE-PWROPT-TIMING" Name="metronome_timing_summary_postplace_pwropted.rpt"/>
  <File Type="POSTPLACE-PWROPT-DCP" Name="metronome_postplace_pwropt.dcp"/>
  <File Type="PLACE-TIMING" Name="metronome_timing_summary_placed.rpt"/>
  <File Type="PLACE-PRE-SIMILARITY" Name="metronome_incremental_reuse_pre_placed.rpt"/>
  <File Type="PLACE-SIMILARITY" Name="metronome_incremental_reuse_placed.rpt"/>
  <File Type="PLACE-CTRL" Name="metronome_control_sets_placed.rpt"/>
  <File Type="PLACE-UTIL-PB" Name="metronome_utilization_placed.pb"/>
  <File Type="PLACE-UTIL" Name="metronome_utilization_placed.rpt"/>
  <File Type="PLACE-CLK" Name="metronome_clock_utilization_placed.rpt"/>
  <File Type="PLACE-IO" Name="metronome_io_placed.rpt"/>
  <File Type="PLACE-DCP" Name="metronome_placed.dcp"/>
  <File Type="PWROPT-TIMING" Name="metronome_timing_summary_pwropted.rpt"/>
  <File Type="PWROPT-DRC" Name="metronome_drc_pwropted.rpt"/>
  <File Type="PWROPT-DCP" Name="metronome_pwropt.dcp"/>
  <File Type="OPT-TIMING" Name="metronome_timing_summary_opted.rpt"/>
  <File Type="OPT-HWDEF" Name="metronome.hwdef"/>
  <File Type="OPT-METHODOLOGY-DRC" Name="metronome_methodology_drc_opted.rpt"/>
  <File Type="OPT-DRC" Name="metronome_drc_opted.rpt"/>
  <File Type="OPT-DCP" Name="metronome_opt.dcp"/>
  <File Type="INIT-TIMING" Name="metronome_timing_summary_init.rpt"/>
  <File Type="ROUTE-BUS-SKEW-RPX" Name="metronome_bus_skew_routed.rpx"/>
  <File Type="REPORTS-TCL" Name="metronome_reports.tcl"/>
  <File Type="ROUTE-BUS-SKEW-PB" Name="metronome_bus_skew_routed.pb"/>
  <File Type="PA-TCL" Name="metronome.tcl"/>
  <FileSet Name="sources" Type="DesignSrcs" RelSrcDir="$PSRCDIR/sources_1">
    <Filter Type="Srcs"/>
    <File Path="$PSRCDIR/sources_1/new/2_to_four_decoder.v">
      <FileInfo>
        <Attr Name="UsedIn" Val="synthesis"/>
        <Attr Name="UsedIn" Val="implementation"/>
        <Attr Name="UsedIn" Val="simulation"/>
      </FileInfo>
    </File>
    <File Path="$PSRCDIR/sources_1/new/bcd7seg.v">
      <FileInfo>
        <Attr Name="UsedIn" Val="synthesis"/>
        <Attr Name="UsedIn" Val="implementation"/>
        <Attr Name="UsedIn" Val="simulation"/>
      </FileInfo>
    </File>
    <File Path="$PSRCDIR/sources_1/new/button.v">
      <FileInfo>
        <Attr Name="UsedIn" Val="synthesis"/>
        <Attr Name="UsedIn" Val="implementation"/>
        <Attr Name="UsedIn" Val="simulation"/>
      </FileInfo>
    </File>
    <File Path="$PSRCDIR/sources_1/new/clk_counter_2bit.v">
      <FileInfo>
        <Attr Name="UsedIn" Val="synthesis"/>
        <Attr Name="UsedIn" Val="implementation"/>
        <Attr Name="UsedIn" Val="simulation"/>
      </FileInfo>
    </File>
    <File Path="$PSRCDIR/sources_1/new/counter_1bit.v">
      <FileInfo>
        <Attr Name="UsedIn" Val="synthesis"/>
        <Attr Name="UsedIn" Val="implementation"/>
        <Attr Name="UsedIn" Val="simulation"/>
      </FileInfo>
    </File>
    <File Path="$PPRDIR/../../../Downloads/Jims_files/counter_2bit.v">
      <FileInfo>
        <Attr Name="UsedIn" Val="synthesis"/>
        <Attr Name="UsedIn" Val="implementation"/>
        <Attr Name="UsedIn" Val="simulation"/>
      </FileInfo>
    </File>
    <File Path="$PSRCDIR/sources_1/new/counter_3bit.v">
      <FileInfo>
        <Attr Name="UsedIn" Val="synthesis"/>
        <Attr Name="UsedIn" Val="implementation"/>
        <Attr Name="UsedIn" Val="simulation"/>
      </FileInfo>
    </File>
    <File Path="$PPRDIR/../../../Downloads/Jims_files/four_by_one_mux.v">
      <FileInfo>
        <Attr Name="UsedIn" Val="synthesis"/>
        <Attr Name="UsedIn" Val="implementation"/>
        <Attr Name="UsedIn" Val="simulation"/>
      </FileInfo>
    </File>
    <File Path="$PSRCDIR/sources_1/new/mux_4x1_2bit.v">
      <FileInfo>
        <Attr Name="UsedIn" Val="synthesis"/>
        <Attr Name="UsedIn" Val="implementation"/>
        <Attr Name="UsedIn" Val="simulation"/>
      </FileInfo>
    </File>
    <File Path="$PPRDIR/../../../Downloads/Jims_files/slowclock.v">
      <FileInfo>
        <Attr Name="UsedIn" Val="synthesis"/>
        <Attr Name="UsedIn" Val="implementation"/>
        <Attr Name="UsedIn" Val="simulation"/>
      </FileInfo>
    </File>
    <File Path="$PSRCDIR/sources_1/new/tempo_selector.v">
      <FileInfo>
        <Attr Name="UsedIn" Val="synthesis"/>
        <Attr Name="UsedIn" Val="implementation"/>
        <Attr Name="UsedIn" Val="simulation"/>
      </FileInfo>
    </File>
    <File Path="$PSRCDIR/sources_1/new/tempo_to_sevenseg.v">
      <FileInfo>
        <Attr Name="UsedIn" Val="synthesis"/>
        <Attr Name="UsedIn" Val="implementation"/>
        <Attr Name="UsedIn" Val="simulation"/>
      </FileInfo>
    </File>
    <File Path="$PSRCDIR/sources_1/new/time_signature_clock.v">
      <FileInfo>
        <Attr Name="UsedIn" Val="synthesis"/>
        <Attr Name="UsedIn" Val="implementation"/>
        <Attr Name="UsedIn" Val="simulation"/>
      </FileInfo>
    </File>
    <File Path="$PSRCDIR/sources_1/new/timesig_to_sevenseg.v">
      <FileInfo>
        <Attr Name="UsedIn" Val="synthesis"/>
        <Attr Name="UsedIn" Val="implementation"/>
        <Attr Name="UsedIn" Val="simulation"/>
      </FileInfo>
    </File>
    <File Path="$PSRCDIR/sources_1/new/two_by_one_mux.v">
      <FileInfo>
        <Attr Name="UsedIn" Val="synthesis"/>
        <Attr Name="UsedIn" Val="implementation"/>
        <Attr Name="UsedIn" Val="simulation"/>
      </FileInfo>
    </File>
    <File Path="$PSRCDIR/sources_1/new/metronome.v">
      <FileInfo>
        <Attr Name="UsedIn" Val="synthesis"/>
        <Attr Name="UsedIn" Val="implementation"/>
        <Attr Name="UsedIn" Val="simulation"/>
      </FileInfo>
    </File>
    <File Path="$PSRCDIR/sources_1/new/counter_2bit.v">
      <FileInfo>
        <Attr Name="AutoDisabled" Val="1"/>
        <Attr Name="UsedIn" Val="synthesis"/>
        <Attr Name="UsedIn" Val="implementation"/>
        <Attr Name="UsedIn" Val="simulation"/>
      </FileInfo>
    </File>
    <File Path="$PSRCDIR/sources_1/new/counter_4bit.v">
      <FileInfo>
        <Attr Name="AutoDisabled" Val="1"/>
        <Attr Name="UsedIn" Val="synthesis"/>
        <Attr Name="UsedIn" Val="implementation"/>
        <Attr Name="UsedIn" Val="simulation"/>
      </FileInfo>
    </File>
    <File Path="$PSRCDIR/sources_1/new/metronome_debug.v">
      <FileInfo>
        <Attr Name="AutoDisabled" Val="1"/>
        <Attr Name="UsedIn" Val="synthesis"/>
        <Attr Name="UsedIn" Val="implementation"/>
        <Attr Name="UsedIn" Val="simulation"/>
      </FileInfo>
    </File>
    <File Path="$PSRCDIR/sources_1/new/slowclock.v">
      <FileInfo>
        <Attr Name="AutoDisabled" Val="1"/>
        <Attr Name="UsedIn" Val="synthesis"/>
        <Attr Name="UsedIn" Val="implementation"/>
        <Attr Name="UsedIn" Val="simulation"/>
      </FileInfo>
    </File>
    <Config>
      <Option Name="DesignMode" Val="RTL"/>
      <Option Name="TopModule" Val="metronome"/>
    </Config>
  </FileSet>
  <FileSet Name="constrs_in" Type="Constrs" RelSrcDir="$PSRCDIR/constrs_1">
    <Filter Type="Constrs"/>
    <File Path="$PSRCDIR/constrs_1/new/constraints.xdc">
      <FileInfo>
        <Attr Name="UsedIn" Val="synthesis"/>
        <Attr Name="UsedIn" Val="implementation"/>
      </FileInfo>
    </File>
    <Config>
      <Option Name="ConstrsType" Val="XDC"/>
    </Config>
  </FileSet>
  <FileSet Name="utils" Type="Utils" RelSrcDir="$PSRCDIR/utils_1">
    <Filter Type="Utils"/>
    <Config>
      <Option Name="TopAutoSet" Val="TRUE"/>
    </Config>
  </FileSet>
  <Strategy Version="1" Minor="2">
    <StratHandle Name="Vivado Implementation Defaults" Flow="Vivado Implementation 2019">
      <Desc>Default settings for Implementation.</Desc>
    </StratHandle>
    <Step Id="init_design"/>
    <Step Id="opt_design"/>
    <Step Id="power_opt_design"/>
    <Step Id="place_design"/>
    <Step Id="post_place_power_opt_design"/>
    <Step Id="phys_opt_design"/>
    <Step Id="route_design"/>
    <Step Id="post_route_phys_opt_design"/>
    <Step Id="write_bitstream">
      <Option Id="BinFile">1</Option>
    </Step>
  </Strategy>
</GenRun>
